{
  "source" : "\u003Ca href=\"http:\/\/twitter.com\" rel=\"nofollow\"\u003ETwitter Web Client\u003C\/a\u003E",
  "entities" : {
    "user_mentions" : [ ],
    "media" : [ ],
    "hashtags" : [ ],
    "urls" : [ ]
  },
  "geo" : { },
  "id_str" : "565203",
  "text" : "Made a little Twitter thing: http:\/\/www.gyford.com\/phil\/writing\/2006\/12\/02\/quick_twitter.php",
  "id" : 565203,
  "created_at" : "2006-12-02 00:00:00 +0000",
  "user" : {
    "name" : "Phil Gyford",
    "screen_name" : "philgyford",
    "protected" : false,
    "id_str" : "12552",
    "profile_image_url_https" : "https:\/\/pbs.twimg.com\/profile_images\/1167616130\/james_200208_300x300_normal.jpg",
    "id" : 12552,
    "verified" : false
  }
}
